[
	{
		"id": 1,
		"title": "Man Gets on Flight Home To Roost",
		"date": "May 25, 2016", 
		"preview": "https://unsplash.it/300/300?image=1081",
		"image": "https://unsplash.it/1000/450?image=1081"
	},
	{
		"id": 2,
		"title": "Stuff Your Brain Into Focusing",
		"date": "May 1, 2016", 
		"preview": "https://unsplash.it/300/300?image=1075",
		"image": "https://unsplash.it/1000/450?image=1075"
	},
	{
		"id": 3,
		"title": "People Are Getting Old School",
		"date": "April 15, 2016", 
		"preview": "https://unsplash.it/1000/450?image=1067",
		"image": "https://unsplash.it/1000/450?image=1067"
	},
	{
		"id": 4,
		"title": "Pentagon Boss Goes to Baghdad",
		"date": "April 9, 2016", 
		"preview": "https://unsplash.it/300/300?image=1051",
		"image": "https://unsplash.it/1000/450?image=1051"
	},
	{
		"id": 5,
		"title": "How To Catch Fugitive Officials",
		"date": "March 8, 2016", 
		"preview": "https://unsplash.it/300/300?image=1033",
		"image": "https://unsplash.it/1000/450?image=1033"
	},
	{
		"id": 6,
		"title": "An Expert Interview About Conservatories",
		"date": "March 3, 2016", 
		"preview": "https://unsplash.it/300/300?image=983",
		"image": "https://unsplash.it/1000/450?image=983"
	},
	{
		"id": 7,
		"title": "How Scientists Are Redefining the Kilogram",
		"date": "February 17, 2016", 
		"preview": "https://unsplash.it/300/300?image=972",
		"image": "https://unsplash.it/1000/450?image=972"
	},
	{
		"id": 8,
		"title": "A Huge Effect on The Opposite Side Of Cries",
		"date": "February 13, 2016", 
		"preview": "https://unsplash.it/300/300?image=953",
		"image": "https://unsplash.it/1000/450?image=953"
	},
	{
		"id": 9,
		"title": "Trump VP Supports Women’s Rights To Vesey",
		"date": "January 1, 2016", 
		"preview": "https://unsplash.it/300/300?image=948",
		"image": "https://unsplash.it/1000/450?image=948"
	}
]